LICENSE.txt
README.md
setup.py
do_random/__init__.py
do_random.egg-info/PKG-INFO
do_random.egg-info/SOURCES.txt
do_random.egg-info/dependency_links.txt
do_random.egg-info/not-zip-safe
do_random.egg-info/top_level.txt
do_random/string/__init__.py