Metadata-Version: 2.1
Name: do-random
Version: 0.0.3
Summary: random and random
Home-page: https://github.com/HowieHz/do_random
Author: HowieHz
License: UNKNOWN
Project-URL: Bug Reports, https://github.com/HowieHz/do_random/issues
Platform: UNKNOWN
Classifier: License :: OSI Approved :: GNU Affero General Public License v3 or later (AGPLv3+)
Classifier: Operating System :: OS Independent
Classifier: Programming Language :: Python :: 3.9
License-File: LICENSE.txt
